{"name":"Mark III","tagline":"A starting point for most of my projects","body":"## Mark Three - Template\r\n---\r\nA set of files I usually use, everytime I start a project.\r\n\r\n### Currently includes\r\n- Normalize v2.1.3\r\n- Bourbon (SASS dependant) v3.1.8\r\n- jQuery v1.10.2\r\n- AngularJS 1.2.10 with Route and Animate Modules\r\n\r\n### CSS (SASS based)\r\n- Edit style.scss\r\n- Link style.css\r\n\r\n#### Running SASS\r\n- Point to the /css folder and run the following SASS command (just once)\r\n```\r\nsass --watch style.scss:style.css --style compressed\r\n```\r\n\r\n- or in WindowsPowerShell, run\r\n```\r\n.\\sass\r\n```\r\n\r\ngoto `// Declare Variables` in style.scss for default variables \r\n\r\nOptionally, run `myth` in the end\r\n```\r\nmyth style.css style.css\r\n```\r\n\r\n### JS (Uglify based)\r\n- Edit script.u.js\r\n- Link script.js\r\n#### Running Uglify.js\r\n\r\n- From the project folder, run (after every update)\r\n```\r\nuglifyjs -o js/script.js js/script.u.js\r\n```\r\n- or in WindowsPowerShell, run\r\n```\r\n.\\ujs\r\n```\r\n\r\n\r\n### Default Font\r\n- Open Sans\r\n\r\n","google":"","note":"Don't delete this file! It's used internally to help with page regeneration."}